versioalueet/__init__.py
versioalueet/__main__.py
versioalueet/api.py
versioalueet/cli.py
versioalueet/env.py
versioalueet-2025.1.8.dist-info/LICENSE
versioalueet-2025.1.8.dist-info/METADATA
versioalueet-2025.1.8.dist-info/WHEEL
versioalueet-2025.1.8.dist-info/entry_points.txt
versioalueet-2025.1.8.dist-info/top_level.txt
versioalueet-2025.1.8.dist-info/RECORD
